src/i2c_master.sv
    module i2c_master #(
    parameter CLK_FREQ = 27_000_000, 
    parameter I2C_FREQ = 100_000     
)(
    input  wire       clk,         
    input  wire       rst_n,       
    input  wire       ena,          
    input  wire [6:0] addr,        
    input  wire       rw,          
    input  wire [7:0] data_wr,     
    input  wire       stop,     

    output reg        busy,    
    output reg  [7:0] data_rd,      
    output reg        ack_error,   

    inout  wire       scl,
    inout  wire       sda
);

    localparam DIVIDER = CLK_FREQ / (I2C_FREQ * 4);

    localparam STATE_IDLE    = 4'd0;
    localparam STATE_START   = 4'd1;
    localparam STATE_ADDR    = 4'd2;
    localparam STATE_SLV_ACK = 4'd3;
    localparam STATE_WRITE   = 4'd4;
    localparam STATE_WR_ACK  = 4'd5;
    localparam STATE_READ    = 4'd6;
    localparam STATE_MSTR_ACK= 4'd7;
    localparam STATE_STOP    = 4'd8;

    reg [3:0]  state;
    reg [15:0] clk_cnt;
    reg [1:0]  phase;          
    reg [2:0]  bit_idx;        
    reg [7:0]  saved_addr_rw;
    reg [7:0]  saved_data;
    reg        saved_stop;
    
    reg scl_enable;
    reg sda_enable; 

    assign scl = scl_enable ? 1'b0 : 1'bz;
    assign sda = sda_enable ? 1'b0 : 1'bz;

    wire cycle_pulse = (clk_cnt == DIVIDER - 1);

    always @(posedge clk or negedge rst_n) begin
        if (!rst_n) begin
            clk_cnt <= 16'd0;
            phase   <= 2'd0;
        end else if (busy) begin
            if (cycle_pulse) begin
                clk_cnt <= 16'd0;
                phase   <= phase + 1'b1;
            end else begin
                clk_cnt <= clk_cnt + 1'b1;
            end
        end else begin
            clk_cnt <= 16'd0;
            phase   <= 2'd0;
        end
    end
    always @(posedge clk or negedge rst_n) begin
        if (!rst_n) begin
            state         <= STATE_IDLE;
            busy          <= 1'b0;
            scl_enable    <= 1'b0;
            sda_enable    <= 1'b0;
            data_rd       <= 8'd0;
            ack_error     <= 1'b0;
            bit_idx       <= 3'd7;
            saved_addr_rw <= 8'd0;
            saved_data    <= 8'd0;
            saved_stop    <= 1'b0;
        end else begin
            case (state)
                STATE_IDLE: begin
                    scl_enable <= 1'b0;
                    sda_enable <= 1'b0; 
                    if (ena) begin
                        busy          <= 1'b1;
                        saved_addr_rw <= {addr, rw};
                        saved_data    <= data_wr;
                        saved_stop    <= stop;
                        ack_error     <= 1'b0;
                        state         <= STATE_START;
                    end else begin
                        busy <= 1'b0;
                    end
                end

                STATE_START: begin
                    if (cycle_pulse) begin
                        case (phase)
                            2'd0: begin sda_enable <= 1'b0; scl_enable <= 1'b0; end
                            2'd1: begin sda_enable <= 1'b1; scl_enable <= 1'b0; end
                            2'd2: begin sda_enable <= 1'b1; scl_enable <= 1'b0; end
                            2'd3: begin 
                                scl_enable <= 1'b1; 
                                bit_idx    <= 3'd7;
                                state      <= STATE_ADDR;
                            end
                        endcase
                    end
                end

                STATE_ADDR: begin
                    if (cycle_pulse) begin
                        case (phase)
                            2'd0: sda_enable <= ~saved_addr_rw[bit_idx]; 
                            2'd1: scl_enable <= 1'b0;                    
                            2'd2: scl_enable <= 1'b0;                   
                            2'd3: begin
                                scl_enable <= 1'b1;                      
                                if (bit_idx == 3'd0) begin
                                    state <= STATE_SLV_ACK;
                                end else begin
                                    bit_idx <= bit_idx - 1'b1;
                                end
                            end
                        endcase
                    end
                end

                STATE_SLV_ACK: begin
                    if (cycle_pulse) begin
                        case (phase)
                            2'd0: sda_enable <= 1'b0; 
                            2'd1: scl_enable <= 1'b0; 
                            2'd2: begin

                                if (sda == 1'b1) ack_error <= 1'b1;
                            end
                            2'd3: begin
                                scl_enable <= 1'b1;
                                bit_idx    <= 3'd7;
                                if (saved_addr_rw[0] == 1'b0)
                                    state <= STATE_WRITE; 
                                else
                                    state <= STATE_READ;  
                            end
                        endcase
                    end
                end

                STATE_WRITE: begin
                    if (cycle_pulse) begin
                        case (phase)
                            2'd0: sda_enable <= ~saved_data[bit_idx];
                            2'd1: scl_enable <= 1'b0;
                            2'd2: scl_enable <= 1'b0;
                            2'd3: begin
                                scl_enable <= 1'b1;
                                if (bit_idx == 3'd0) begin
                                    state <= STATE_WR_ACK;
                                end else begin
                                    bit_idx <= bit_idx - 1'b1;
                                end
                            end
                        endcase
                    end
                end

                STATE_WR_ACK: begin
                    if (cycle_pulse) begin
                        case (phase)
                            2'd0: sda_enable <= 1'b0;
                            2'd1: scl_enable <= 1'b0;
                            2'd2: begin
                                if (sda == 1'b1) ack_error <= 1'b1;
                            end
                            2'd3: begin
                                scl_enable <= 1'b1;
                                if (saved_stop)
                                    state <= STATE_STOP;
                                else
                                    state <= STATE_IDLE;
                            end
                        endcase
                    end
                end

                STATE_READ: begin
                    if (cycle_pulse) begin
                        case (phase)
                            2'd0: sda_enable <= 1'b0; 
                            2'd1: scl_enable <= 1'b0;
                            2'd2: data_rd[bit_idx] <= sda; 
                            2'd3: begin
                                scl_enable <= 1'b1; 
                                if (bit_idx == 3'd0) begin
                                    state <= STATE_MSTR_ACK;
                                end else begin
                                    bit_idx <= bit_idx - 1'b1;
                                end
                            end
                        endcase
                    end
                end

                STATE_MSTR_ACK: begin
                    if (cycle_pulse) begin
                        case (phase)
                            2'd0: sda_enable <= 1'b0; 
                            2'd1: scl_enable <= 1'b0;
                            2'd2: scl_enable <= 1'b0;
                            2'd3: begin
                                scl_enable <= 1'b1;
                                state      <= STATE_STOP;
                            end
                        endcase
                    end
                end

                STATE_STOP: begin
                    if (cycle_pulse) begin
                        case (phase)
                            2'd0: begin sda_enable <= 1'b1; scl_enable <= 1'b1; end
                            2'd1: begin sda_enable <= 1'b1; scl_enable <= 1'b0; end 
                            2'd2: begin sda_enable <= 1'b0; scl_enable <= 1'b0; end 
                            2'd3: begin
                                busy  <= 1'b0;
                                state <= STATE_IDLE;
                            end
                        endcase
                    end
                end

                default: state <= STATE_IDLE;
            endcase
        end
    end

endmodule

simulation/tb_i2c_master.v
`timescale 1ns/1ps

module tb_i2c_master;

    localparam CLK_PERIOD = 37; // ~27MHz

    reg        clk;
    reg        rst_n;
    reg        ena;
    reg [6:0]  addr;
    reg        rw;
    reg [7:0]  data_wr;
    reg        stop;

    wire       busy;
    wire [7:0] data_rd;
    wire       ack_error;
    wire       scl;
    wire       sda;

    // Trở kéo pull-up cho bus I2C chuẩn Open-Drain
    pullup (scl);
    pullup (sda);

    // Slave model: điều khiển kéo SDA xuống 0 khi ACK
    reg sda_slave_en;
    assign sda = sda_slave_en ? 1'b0 : 1'bz;

    // Khởi tạo DUT
    i2c_master #(
        .CLK_FREQ(27_000_000),
        .I2C_FREQ(100_000)
    ) dut (
        .clk      (clk),
        .rst_n    (rst_n),
        .ena      (ena),
        .addr     (addr),
        .rw       (rw),
        .data_wr  (data_wr),
        .stop     (stop),
        .busy     (busy),
        .data_rd  (data_rd),
        .ack_error(ack_error),
        .scl      (scl),
        .sda      (sda)
    );

    // Tạo xung Clock 27MHz
    initial clk = 0;
    always #(CLK_PERIOD/2) clk = ~clk;

    task wait_cycles;
        input integer n;
        integer i;
        begin
            for (i = 0; i < n; i = i + 1)
                @(posedge clk);
        end
    endtask

    // Theo dõi trạng thái FSM nội bộ của DUT
    wire [3:0] dut_state = dut.state;

    localparam ST_SLV_ACK = 4'd3;
    localparam ST_WR_ACK  = 4'd5;

    reg do_ack;

    // Giữ SDA = 0 trong toàn bộ thời gian của ST_SLV_ACK và ST_WR_ACK
    // để DUT lấy mẫu chính xác ở phase 2
    always @(*) begin
        if (do_ack && (dut_state == ST_SLV_ACK || dut_state == ST_WR_ACK))
            sda_slave_en = 1'b1;
        else
            sda_slave_en = 1'b0;
    end

    // Task phát lệnh ghi 1 byte I2C
    task i2c_write;
        input [6:0] t_addr;
        input [7:0] t_data;
        input       t_stop;
        input       t_ack;
        begin
            do_ack  = t_ack;
            addr    = t_addr;
            rw      = 1'b0;
            data_wr = t_data;
            stop    = t_stop;
            ena     = 1'b1;
            @(posedge clk); #1;
            ena     = 1'b0;

            // Chờ Master bắt đầu và kết thúc truyền
            wait(busy == 1'b1);
            wait(busy == 1'b0);
            #1;

            do_ack  = 1'b0;
        end
    endtask

    // Task kiểm tra kết quả
    task check_result;
        input integer tid;
        input         exp_err;
        begin
            $write("TEST %0d: ack_error=%b | ", tid, ack_error);
            if (ack_error == exp_err)
                $display("PASS");
            else
                $display("FAIL (expected %b)", exp_err);
        end
    endtask

    always @(negedge busy) begin
        if (rst_n)
            $display("  [%0t ns] Done ack_error=%b", $time, ack_error);
    end

    // Kịch bản kiểm thử
    initial begin
        rst_n        = 0;
        ena          = 0;
        addr         = 7'h00;
        rw           = 0;
        data_wr      = 8'h00;
        stop         = 1;
        sda_slave_en = 0;
        do_ack       = 0;

        wait_cycles(10);
        rst_n = 1;
        wait_cycles(5);

        $display("=== TEST 1: Write 0x00 addr=0x3C ACK ===");
        i2c_write(7'h3C, 8'h00, 1'b0, 1'b1);
        check_result(1, 1'b0);
        wait_cycles(10);

        $display("=== TEST 2: Write 0xAE ACK ===");
        i2c_write(7'h3C, 8'hAE, 1'b1, 1'b1);
        check_result(2, 1'b0);
        wait_cycles(10);

        $display("=== TEST 3: Write 0x40 ACK ===");
        i2c_write(7'h3C, 8'h40, 1'b0, 1'b1);
        check_result(3, 1'b0);
        wait_cycles(10);

        $display("=== TEST 4: Write 0xFF ACK ===");
        i2c_write(7'h3C, 8'hFF, 1'b1, 1'b1);
        check_result(4, 1'b0);
        wait_cycles(10);

        $display("=== TEST 5: NACK expected ===");
        i2c_write(7'h3C, 8'hAF, 1'b1, 1'b0);
        check_result(5, 1'b1);
        wait_cycles(10);

        $display("=== ALL DONE ===");
        $finish;
    end

    // Timeout dự phòng
    initial begin
        #2_000_000_000; // 2 giây mô phỏng
        $display("TIMEOUT");
        $finish;
    end

    // Xuất file VCD
    initial begin
        $dumpfile("tb_i2c_master.vcd");
        $dumpvars(0, tb_i2c_master);
    end

endmodule

simulation/tb_i2c_master.vcd
$date
	Mon Sep 21 11:17:27 2026
$end
$version
	Icarus Verilog
$end
$timescale
	1ps
$end
$scope module tb_i2c_master $end
$var wire 4 ! dut_state [3:0] $end
$var wire 1 " scl $end
$var wire 1 # sda $end
$var wire 8 $ data_rd [7:0] $end
$var wire 1 % busy $end
$var wire 1 & ack_error $end
$var parameter 32 ' CLK_PERIOD $end
$var parameter 4 ( ST_SLV_ACK $end
$var parameter 4 ) ST_WR_ACK $end
$var reg 7 * addr [6:0] $end
$var reg 1 + clk $end
$var reg 8 , data_wr [7:0] $end
$var reg 1 - do_ack $end
$var reg 1 . ena $end
$var reg 1 / rst_n $end
$var reg 1 0 rw $end
$var reg 1 1 sda_slave_en $end
$var reg 1 2 stop $end
$scope module dut $end
$var wire 7 3 addr [6:0] $end
$var wire 1 + clk $end
$var wire 8 4 data_wr [7:0] $end
$var wire 1 . ena $end
$var wire 1 / rst_n $end
$var wire 1 0 rw $end
$var wire 1 " scl $end
$var wire 1 # sda $end
$var wire 1 2 stop $end
$var wire 1 5 cycle_pulse $end
$var parameter 32 6 CLK_FREQ $end
$var parameter 64 7 DIVIDER $end
$var parameter 32 8 I2C_FREQ $end
$var parameter 4 9 STATE_ADDR $end
$var parameter 4 : STATE_IDLE $end
$var parameter 4 ; STATE_MSTR_ACK $end
$var parameter 4 < STATE_READ $end
$var parameter 4 = STATE_SLV_ACK $end
$var parameter 4 > STATE_START $end
$var parameter 4 ? STATE_STOP $end
$var parameter 4 @ STATE_WRITE $end
$var parameter 4 A STATE_WR_ACK $end
$var reg 1 & ack_error $end
$var reg 3 B bit_idx [2:0] $end
$var reg 1 % busy $end
$var reg 16 C clk_cnt [15:0] $end
$var reg 8 D data_rd [7:0] $end
$var reg 2 E phase [1:0] $end
$var reg 8 F saved_addr_rw [7:0] $end
$var reg 8 G saved_data [7:0] $end
$var reg 1 H saved_stop $end
$var reg 1 I scl_enable $end
$var reg 1 J sda_enable $end
$var reg 4 K state [3:0] $end
$upscope $end
$scope task check_result $end
$var reg 1 L exp_err $end
$var integer 32 M tid [31:0] $end
$upscope $end
$scope task i2c_write $end
$var reg 1 N t_ack $end
$var reg 7 O t_addr [6:0] $end
$var reg 8 P t_data [7:0] $end
$var reg 1 Q t_stop $end
$upscope $end
$scope task wait_cycles $end
$var integer 32 R i [31:0] $end
$var integer 32 S n [31:0] $end
$upscope $end
$upscope $end
$enddefinitions $end
$comment Show the parameter values. $end
$dumpall
b101 A
b100 @
b1000 ?
b1 >
b11 =
b110 <
b111 ;
b0 :
b10 9
b11000011010100000 8
b1000011 7
b1100110111111110011000000 6
b101 )
b11 (
b100101 '
$end
#0
$dumpvars
b1010 S
b0 R
xQ
bx P
bx O
xN
bx M
xL
b0 K
0J
0I
0H
b0 G
b0 F
b0 E
b0 D
b0 C
b111 B
05
b0 4
b0 3
12
01
00
0/
0.
0-
b0 ,
0+
b0 *
0&
0%
b0 $
1#
1"
b0 !
$end
#18000
b1 R
1+
#36000
0+
#54000
b10 R
1+
#72000
0+
#90000
b11 R
1+
#108000
0+
#126000
b100 R
1+
#144000
0+
#162000
b101 R
1+
#180000
0+
#198000
b110 R
1+
#216000
0+
#234000
b111 R
1+
#252000
0+
#270000
b1000 R
1+
#288000
0+
#306000
b1001 R
1+
#324000
0+
#342000
b101 S
1/
b0 R
1+
#360000
0+
#378000
b1 R
1+
#396000
0+
#414000
b10 R
1+
#432000
0+
#450000
b11 R
1+
#468000
0+
#486000
b100 R
1+
#504000
0+
#522000
b1 !
b1 K
b1111000 F
1%
1.
02
b111100 *
b111100 3
1-
1N
0Q
b0 P
b111100 O
b101 R
1+
#540000
0+
#558000
b1 C
1+
#559000
0.
#576000
0+
#594000
b10 C
1+
#612000
0+
#630000
b11 C
1+
#648000
0+
#666000
b100 C
1+
#684000
0+
#702000
b101 C
1+
#720000
0+
#738000
b110 C
1+
#756000
0+
#774000
b111 C
1+
#792000
0+
#810000
b1000 C
1+
#828000
0+
#846000
b1001 C
1+
#864000
0+
#882000
b1010 C
1+
#900000
0+
#918000
b1011 C
1+
#936000
0+
#954000
b1100 C
1+
#972000
0+
#990000
b1101 C
1+
#1008000
0+
#1026000
b1110 C
1+
#1044000
0+
#1062000
b1111 C
1+
#1080000
0+
#1098000
b10000 C
1+
#1116000
0+
#1134000
b10001 C
1+
#1152000
0+
#1170000
b10010 C
1+
#1188000
0+
#1206000
b10011 C
1+
#1224000
0+
#1242000
b10100 C
1+
#1260000
0+
#1278000
b10101 C
1+
#1296000
0+
#1314000
b10110 C
1+
#1332000
0+
#1350000
b10111 C
1+
#1368000
0+
#1386000
b11000 C
1+
#1404000
0+
#1422000
b11001 C
1+
#1440000
0+
#1458000
b11010 C
1+
#1476000
0+
#1494000
b11011 C
1+
#1512000
0+
#1530000
b11100 C
1+
#1548000
0+
#1566000
b11101 C
1+
#1584000
0+
#1602000
b11110 C
1+
#1620000
0+
#1638000
b11111 C
1+
#1656000
0+
#1674000
b100000 C
1+
#1692000
0+
#1710000
b100001 C
1+
#1728000
0+
#1746000
b100010 C
1+
#1764000
0+
#1782000
b100011 C
1+
#1800000
0+
#1818000
b100100 C
1+
#1836000
0+
#1854000
b100101 C
1+
#1872000
0+
#1890000
b100110 C
1+
#1908000
0+
#1926000
b100111 C
1+
#1944000
0+
#1962000
b101000 C
1+
#1980000
0+
#1998000
b101001 C
1+
#2016000
0+
#2034000
b101010 C
1+
#2052000
0+
#2070000
b101011 C
1+
#2088000
0+
#2106000
b101100 C
1+
#2124000
0+
#2142000
b101101 C
1+
#2160000
0+
#2178000
b101110 C
1+
#2196000
0+
#2214000
b101111 C
1+
#2232000
0+
#2250000
b110000 C
1+
#2268000
0+
#2286000
b110001 C
1+
#2304000
0+
#2322000
b110010 C
1+
#2340000
0+
#2358000
b110011 C
1+
#2376000
0+
#2394000
b110100 C
1+
#2412000
0+
#2430000
b110101 C
1+
#2448000
0+
#2466000
b110110 C
1+
#2484000
0+
#2502000
b110111 C
1+
#2520000
0+
#2538000
b111000 C
1+
#2556000
0+
#2574000
b111001 C
1+
#2592000
0+
#2610000
b111010 C
1+
#2628000
0+
#2646000
b111011 C
1+
#2664000
0+
#2682000
b111100 C
1+
#2700000
0+
#2718000
b111101 C
1+
#2736000
0+
#2754000
b111110 C
1+
#2772000
0+
#2790000
b111111 C
1+
#2808000
0+
#2826000
b1000000 C
1+
#2844000
0+
#2862000
b1000001 C
1+
#2880000
0+
#2898000
15
b1000010 C
1+
#2916000
0+
#2934000
b1 E
05
b0 C
1+
#2952000
0+
#2970000
b1 C
1+
#2988000
0+
#3006000
b10 C
1+
#3024000
0+
#3042000
b11 C
1+
#3060000
0+
#3078000
b100 C
1+
#3096000
0+
#3114000
b101 C
1+
#3132000
0+
#3150000
b110 C
1+
#3168000
0+
#3186000
b111 C
1+
#3204000
0+
#3222000
b1000 C
1+
#3240000
0+
#3258000
b1001 C
1+
#3276000
0+
#3294000
b1010 C
1+
#3312000
0+
#3330000
b1011 C
1+
#3348000
0+
#3366000
b1100 C
1+
#3384000
0+
#3402000
b1101 C
1+
#3420000
0+
#3438000
b1110 C
1+
#3456000
0+
#3474000
b1111 C
1+
#3492000
0+
#3510000
b10000 C
1+
#3528000
0+
#3546000
b10001 C
1+
#3564000
0+
#3582000
b10010 C
1+
#3600000
0+
#3618000
b10011 C
1+
#3636000
0+
#3654000
b10100 C
1+
#3672000
0+
#3690000
b10101 C
1+
#3708000
0+
#3726000
b10110 C
1+
#3744000
0+
#3762000
b10111 C
1+
#3780000
0+
#3798000
b11000 C
1+
#3816000
0+
#3834000
b11001 C
1+
#3852000
0+
#3870000
b11010 C
1+
#3888000
0+
#3906000
b11011 C
1+
#3924000
0+
#3942000
b11100 C
1+
#3960000
0+
#3978000
b11101 C
1+
#3996000
0+
#4014000
b11110 C
1+
#4032000
0+
#4050000
b11111 C
1+
#4068000
0+
#4086000
b100000 C
1+
#4104000
0+
#4122000
b100001 C
1+
#4140000
0+
#4158000
b100010 C
1+
#4176000
0+
#4194000
b100011 C
1+
#4212000
0+
#4230000
b100100 C
1+
#4248000
0+
#4266000
b100101 C
1+
#4284000
0+
#4302000
b100110 C
1+
#4320000
0+
#4338000
b100111 C
1+
#4356000
0+
#4374000
b101000 C
1+
#4392000
0+
#4410000
b101001 C
1+
#4428000
0+
#4446000
b101010 C
1+
#4464000
0+
#4482000
b101011 C
1+
#4500000
0+
#4518000
b101100 C
1+
#4536000
0+
#4554000
b101101 C
1+
#4572000
0+
#4590000
b101110 C
1+
#4608000
0+
#4626000
b101111 C
1+
#4644000
0+
#4662000
b110000 C
1+
#4680000
0+
#4698000
b110001 C
1+
#4716000
0+
#4734000
b110010 C
1+
#4752000
0+
#4770000
b110011 C
1+
#4788000
0+
#4806000
b110100 C
1+
#4824000
0+
#4842000
b110101 C
1+
#4860000
0+
#4878000
b110110 C
1+
#4896000
0+
#4914000
b110111 C
1+
#4932000
0+
#4950000
b111000 C
1+
#4968000
0+
#4986000
b111001 C
1+
#5004000
0+
#5022000
b111010 C
1+
#5040000
0+
#5058000
b111011 C
1+
#5076000
0+
#5094000
b111100 C
1+
#5112000
0+
#5130000
b111101 C
1+
#5148000
0+
#5166000
b111110 C
1+
#5184000
0+
#5202000
b111111 C
1+
#5220000
0+
#5238000
b1000000 C
1+
#5256000
0+
#5274000
b1000001 C
1+
#5292000
0+
#5310000
15
b1000010 C
1+
#5328000
0+
#5346000
0#
1J
b10 E
05
b0 C
1+
#5364000
0+
#5382000
b1 C
1+
#5400000
0+
#5418000
b10 C
1+
#5436000
0+
#5454000
b11 C
1+
#5472000
0+
#5490000
b100 C
1+
#5508000
0+
#5526000
b101 C
1+
#5544000
0+
#5562000
b110 C
1+
#5580000
0+
#5598000
b111 C
1+
#5616000
0+
#5634000
b1000 C
1+
#5652000
0+
#5670000
b1001 C
1+
#5688000
0+
#5706000
b1010 C
1+
#5724000
0+
#5742000
b1011 C
1+
#5760000
0+
#5778000
b1100 C
1+
#5796000
0+
#5814000
b1101 C
1+
#5832000
0+
#5850000
b1110 C
1+
#5868000
0+
#5886000
b1111 C
1+
#5904000
0+
#5922000
b10000 C
1+
#5940000
0+
#5958000
b10001 C
1+
#5976000
0+
#5994000
b10010 C
1+
#6012000
0+
#6030000
b10011 C
1+
#6048000
0+
#6066000
b10100 C
1+
#6084000
0+
#6102000
b10101 C
1+
#6120000
0+
#6138000
b10110 C
1+
#6156000
0+
#6174000
b10111 C
1+
#6192000
0+
#6210000
b11000 C
1+
#6228000
0+
#6246000
b11001 C
1+
#6264000
0+
#6282000
b11010 C
1+
#6300000
0+
#6318000
b11011 C
1+
#6336000
0+
#6354000
b11100 C
1+
#6372000
0+
#6390000
b11101 C
1+
#6408000
0+
#6426000
b11110 C
1+
#6444000
0+
#6462000
b11111 C
1+
#6480000
0+
#6498000
b100000 C
1+
#6516000
0+
#6534000
b100001 C
1+
#6552000
0+
#6570000
b100010 C
1+
#6588000
0+
#6606000
b100011 C
1+
#6624000
0+
#6642000
b100100 C
1+
#6660000
0+
#6678000
b100101 C
1+
#6696000
0+
#6714000
b100110 C
1+
#6732000
0+
#6750000
b100111 C
1+
#6768000
0+
#6786000
b101000 C
1+
#6804000
0+
#6822000
b101001 C
1+
#6840000
0+
#6858000
b101010 C
1+
#6876000
0+
#6894000
b101011 C
1+
#6912000
0+
#6930000
b101100 C
1+
#6948000
0+
#6966000
b101101 C
1+
#6984000
0+
#7002000
b101110 C
1+
#7020000
0+
#7038000
b101111 C
1+
#7056000
0+
#7074000
b110000 C
1+
#7092000
0+
#7110000
b110001 C
1+
#7128000
0+
#7146000
b110010 C
1+
#7164000
0+
#7182000
b110011 C
1+
#7200000
0+
#7218000
b110100 C
1+
#7236000
0+
#7254000
b110101 C
1+
#7272000
0+
#7290000
b110110 C
1+
#7308000
0+
#7326000
b110111 C
1+
#7344000
0+
#7362000
b111000 C
1+
#7380000
0+
#7398000
b111001 C
1+
#7416000
0+
#7434000
b111010 C
1+
#7452000
0+
#7470000
b111011 C
1+
#7488000
0+
#7506000
b111100 C
1+
#7524000
0+
#7542000
b111101 C
1+
#7560000
0+
#7578000
b111110 C
1+
#7596000
0+
#7614000
b111111 C
1+
#7632000
0+
#7650000
b1000000 C
1+
#7668000
0+
#7686000
b1000001 C
1+
#7704000
0+
#7722000
15
b1000010 C
1+
#7740000
0+
#7758000
b11 E
05
b0 C
1+
#7776000
0+
#7794000
b1 C
1+
#7812000
0+
#7830000
b10 C
1+
#7848000
0+
#7866000
b11 C
1+
#7884000
0+
#7902000
b100 C
1+
#7920000
0+
#7938000
b101 C
1+
#7956000
0+
#7974000
b110 C
1+
#7992000
0+
#8010000
b111 C
1+
#8028000
0+
#8046000
b1000 C
1+
#8064000
0+
#8082000
b1001 C
1+
#8100000
0+
#8118000
b1010 C
1+
#8136000
0+
#8154000
b1011 C
1+
#8172000
0+
#8190000
b1100 C
1+
#8208000
0+
#8226000
b1101 C
1+
#8244000
0+
#8262000
b1110 C
1+
#8280000
0+
#8298000
b1111 C
1+
#8316000
0+
#8334000
b10000 C
1+
#8352000
0+
#8370000
b10001 C
1+
#8388000
0+
#8406000
b10010 C
1+
#8424000
0+
#8442000
b10011 C
1+
#8460000
0+
#8478000
b10100 C
1+
#8496000
0+
#8514000
b10101 C
1+
#8532000
0+
#8550000
b10110 C
1+
#8568000
0+
#8586000
b10111 C
1+
#8604000
0+
#8622000
b11000 C
1+
#8640000
0+
#8658000
b11001 C
1+
#8676000
0+
#8694000
b11010 C
1+
#8712000
0+
#8730000
b11011 C
1+
#8748000
0+
#8766000
b11100 C
1+
#8784000
0+
#8802000
b11101 C
1+
#8820000
0+
#8838000
b11110 C
1+
#8856000
0+
#8874000
b11111 C
1+
#8892000
0+
#8910000
b100000 C
1+
#8928000
0+
#8946000
b100001 C
1+
#8964000
0+
#8982000
b100010 C
1+
#9000000
0+
#9018000
b100011 C
1+
#9036000
0+
#9054000
b100100 C
1+
#9072000
0+
#9090000
b100101 C
1+
#9108000
0+
#9126000
b100110 C
1+
#9144000
0+
#9162000
b100111 C
1+
#9180000
0+
#9198000
b101000 C
1+
#9216000
0+
#9234000
b101001 C
1+
#9252000
0+
#9270000
b101010 C
1+
#9288000
0+
#9306000
b101011 C
1+
#9324000
0+
#9342000
b101100 C
1+
#9360000
0+
#9378000
b101101 C
1+
#9396000
0+
#9414000
b101110 C
1+
#9432000
0+
#9450000
b101111 C
1+
#9468000
0+
#9486000
b110000 C
1+
#9504000
0+
#9522000
b110001 C
1+
#9540000
0+
#9558000
b110010 C
1+
#9576000
0+
#9594000
b110011 C
1+
#9612000
0+
#9630000
b110100 C
1+
#9648000
0+
#9666000
b110101 C
1+
#9684000
0+
#9702000
b110110 C
1+
#9720000
0+
#9738000
b110111 C
1+
#9756000
0+
#9774000
b111000 C
1+
#9792000
0+
#9810000
b111001 C
1+
#9828000
0+
#9846000
b111010 C
1+
#9864000
0+
#9882000
b111011 C
1+
#9900000
0+
#9918000
b111100 C
1+
#9936000
0+
#9954000
b111101 C
1+
#9972000
0+
#9990000
b111110 C
1+
#10008000
0+
#10026000
b111111 C
1+
#10044000
0+
#10062000
b1000000 C
1+
#10080000
0+
#10098000
b1000001 C
1+
#10116000
0+
#10134000
15
b1000010 C
1+
#10152000
0+
#10170000
0"
b10 !
b10 K
1I
b0 E
05
b0 C
1+
#10188000
0+
#10206000
b1 C
1+
#10224000
0+
#10242000
b10 C
1+
#10260000
0+
#10278000
b11 C
1+
#10296000
0+
#10314000
b100 C
1+
#10332000
0+
#10350000
b101 C
1+
#10368000
0+
#10386000
b110 C
1+
#10404000
0+
#10422000
b111 C
1+
#10440000
0+
#10458000
b1000 C
1+
#10476000
0+
#10494000
b1001 C
1+
#10512000
0+
#10530000
b1010 C
1+
#10548000
0+
#10566000
b1011 C
1+
#10584000
0+
#10602000
b1100 C
1+
#10620000
0+
#10638000
b1101 C
1+
#10656000
0+
#10674000
b1110 C
1+
#10692000
0+
#10710000
b1111 C
1+
#10728000
0+
#10746000
b10000 C
1+
#10764000
0+
#10782000
b10001 C
1+
#10800000
0+
#10818000
b10010 C
1+
#10836000
0+
#10854000
b10011 C
1+
#10872000
0+
#10890000
b10100 C
1+
#10908000
0+
#10926000
b10101 C
1+
#10944000
0+
#10962000
b10110 C
1+
#10980000
0+
#10998000
b10111 C
1+
#11016000
0+
#11034000
b11000 C
1+
#11052000
0+
#11070000
b11001 C
1+
#11088000
0+
#11106000
b11010 C
1+
#11124000
0+
#11142000
b11011 C
1+
#11160000
0+
#11178000
b11100 C
1+
#11196000
0+
#11214000
b11101 C
1+
#11232000
0+
#11250000
b11110 C
1+
#11268000
0+
#11286000
b11111 C
1+
#11304000
0+
#11322000
b100000 C
1+
#11340000
0+
#11358000
b100001 C
1+
#11376000
0+
#11394000
b100010 C
1+
#11412000
0+
#11430000
b100011 C
1+
#11448000
0+
#11466000
b100100 C
1+
#11484000
0+
#11502000
b100101 C
1+
#11520000
0+
#11538000
b100110 C
1+
#11556000
0+
#11574000
b100111 C
1+
#11592000
0+
#11610000
b101000 C
1+
#11628000
0+
#11646000
b101001 C
1+
#11664000
0+
#11682000
b101010 C
1+
#11700000
0+
#11718000
b101011 C
1+
#11736000
0+
#11754000
b101100 C
1+
#11772000
0+
#11790000
b101101 C
1+
#11808000
0+
#11826000
b101110 C
1+
#11844000
0+
#11862000
b101111 C
1+
#11880000
0+
#11898000
b110000 C
1+
#11916000
0+
#11934000
b110001 C
1+
#11952000
0+
#11970000
b110010 C
1+
#11988000
0+
#12006000
b110011 C
1+
#12024000
0+
#12042000
b110100 C
1+
#12060000
0+
#12078000
b110101 C
1+
#12096000
0+
#12114000
b110110 C
1+
#12132000
0+
#12150000
b110111 C
1+
#12168000
0+
#12186000
b111000 C
1+
#12204000
0+
#12222000
b111001 C
1+
#12240000
0+
#12258000
b111010 C
1+
#12276000
0+
#12294000
b111011 C
1+
#12312000
0+
#12330000
b111100 C
1+
#12348000
0+
#12366000
b111101 C
1+
#12384000
0+
#12402000
b111110 C
1+
#12420000
0+
#12438000
b111111 C
1+
#12456000
0+
#12474000
b1000000 C
1+
#12492000
0+
#12510000
b1000001 C
1+
#12528000
0+
#12546000
15
b1000010 C
1+
#12564000
0+
#12582000
b1 E
05
b0 C
1+
#12600000
0+
#12618000
b1 C
1+
#12636000
0+
#12654000
b10 C
1+
#12672000
0+
#12690000
b11 C
1+
#12708000
0+
#12726000
b100 C
1+
#12744000
0+
#12762000
b101 C
1+
#12780000
0+
#12798000
b110 C
1+
#12816000
0+
#12834000
b111 C
1+
#12852000
0+
#12870000
b1000 C
1+
#12888000
0+
#12906000
b1001 C
1+
#12924000
0+
#12942000
b1010 C
1+
#12960000
0+
#12978000
b1011 C
1+
#12996000
0+
#13014000
b1100 C
1+
#13032000
0+
#13050000
b1101 C
1+
#13068000
0+
#13086000
b1110 C
1+
#13104000
0+
#13122000
b1111 C
1+
#13140000
0+
#13158000
b10000 C
1+
#13176000
0+
#13194000
b10001 C
1+
#13212000
0+
#13230000
b10010 C
1+
#13248000
0+
#13266000
b10011 C
1+
#13284000
0+
#13302000
b10100 C
1+
#13320000
0+
#13338000
b10101 C
1+
#13356000
0+
#13374000
b10110 C
1+
#13392000
0+
#13410000
b10111 C
1+
#13428000
0+
#13446000
b11000 C
1+
#13464000
0+
#13482000
b11001 C
1+
#13500000
0+
#13518000
b11010 C
1+
#13536000
0+
#13554000
b11011 C
1+
#13572000
0+
#13590000
b11100 C
1+
#13608000
0+
#13626000
b11101 C
1+
#13644000
0+
#13662000
b11110 C
1+
#13680000
0+
#13698000
b11111 C
1+
#13716000
0+
#13734000
b100000 C
1+
#13752000
0+
#13770000
b100001 C
1+
#13788000
0+
#13806000
b100010 C
1+
#13824000
0+
#13842000
b100011 C
1+
